Metadata-Version: 2.1
Name: sparsedist
Version: 0.0.3
Summary: faster parallel pairwise sparse distance
Home-page: https://github.com/pbcquoc/sparsedist
Author: pbcquoc
Author-email: pbcquoc@gmail.com
License: UNKNOWN
Platform: UNKNOWN
Classifier: Programming Language :: Python :: 3
Classifier: License :: OSI Approved :: MIT License
Classifier: Operating System :: OS Independent
Requires-Python: >=3.6
License-File: LICENSE
